LICENSE
MANIFEST.in
README.rst
requirements.txt
setup.cfg
setup.py
time_sheet/__init__.py
time_sheet/__main__.py
time_sheet/take_a_snap.py
time_sheet/time_sheet.py
time_sheet.egg-info/LICENSE
time_sheet.egg-info/PKG-INFO
time_sheet.egg-info/README.rst
time_sheet.egg-info/SOURCES.txt
time_sheet.egg-info/dependency_links.txt
time_sheet.egg-info/entry_points.txt
time_sheet.egg-info/requirements.txt
time_sheet.egg-info/requires.txt
time_sheet.egg-info/sample.json
time_sheet.egg-info/setup.cfg
time_sheet.egg-info/setup.py
time_sheet.egg-info/take_a_snap.py
time_sheet.egg-info/top_level.txt