Metadata-Version: 1.1
Name: time-sheet
Version: 1.0.7
Summary: Python Script to calculate the number of hours you sit before your system. It is a ready-to-run code! 
Home-page: https://github.com/NoSkillGuy/time_sheet
Author: Siva Praveen Rayapudi
Author-email: rsivapraveen001@gmail.com
License: MIT
Download-URL: https://github.com/NoSkillGuy/time_sheet/tarball/1.0.7
Keywords: time-sheet face-recognition snapshot face-detection face detection recognition terminal command-line time hours minutes seconds work
Platform: UNKNOWN
Classifier: Development Status :: 4 - Beta
Classifier: Intended Audience :: Developers
Classifier: License :: OSI Approved :: MIT License
Classifier: Programming Language :: Python :: 2.7
Classifier: Programming Language :: Python :: 3.3
Classifier: Programming Language :: Python :: 3.4
Classifier: Programming Language :: Python :: 3.5
Classifier: Programming Language :: Python :: 3.6
